[
    {
        "punny": "i'm soy into you",
        "image": "https://i.imgur.com/LSJcXTQ.png"
    },
    {
        "punny": "love you, pho real",
        "image": "https://i.imgur.com/JdqY8IA.jpg"
    },
    {
        "punny": "i hate it when bay leaves",
        "image": "https://i.imgur.com/FYgKxIy.png"
    },
    {
        "punny": "keep calm and curry on",
        "image": "https://i.imgur.com/14KuCau.jpg"
    },
    {
        "punny": "sorry i was salty",
        "image": "https://i.imgur.com/OVpSlWL.png"
    }
]